{"id":"22624B6B-B163-4835-9ACD-142D943F475C","validationEntity":{"analysedDataType":"auto","dataResult":{"createdDate":"2023-04-18T08:01:46Z"}},"modelEntity":{"createdDate":"2023-04-18T07:40:11Z","id":"450A67AE-A4AB-4282-B1B3-5B275E03922F","experimentID":"22624B6B-B163-4835-9ACD-142D943F475C","title":"","modifiedDate":"2023-04-18T07:40:11Z","preferredFilename":"","version":"1.0","modelURL":"Models\/BetterRest%201.mlmodel"},"version":"1.0","settingEntity":{"augmentations":[],"suggestedColumns":["wake","estimatedSleep","coffee","actualSleep"],"targetColumn":"actualSleep","seedType":"default","transferLearningEmbeddingType":"dynamic","handPoseClassifierAugmentations":[],"featureNames":["wake","estimatedSleep","coffee"],"algorithmType":"maxEnt","harVideoAugmentations":0,"taskType":"generalRegresor","suggestedColumnValues":["31 500, 32 400, 26 100, 40 500, 19 800, 27 000, 20 700, 21 600, 41 400, 34 200, 21 600, 78 300, 32 400, 28 800, 18 900, 18 000, 28 800, 18 000, 7 200, 35 100, 24 300, 35 100, 34 200, 27 900, 30 600, 69 300, 35 100, 34 200, 34 200, 23 400","9,00, 5,00, 6,50, 8,75, 6,00, 7,50, 9,25, 6,00, 9,25, 6,75, 5,25, 9,25, 10,00, 8,75, 8,25, 6,25, 10,00, 6,25, 10,00, 9,50, 5,00, 7,50, 6,25, 8,00, 8,00, 6,50, 8,00, 10,00, 8,25, 8,00","6, 2, 10, 4, 3, 1, 1, 3, 5, 8, 3, 8, 2, 3, 1, 2, 3, 2, 1, 4, 2, 1, 1, 4, 3, 7, 4, 4, 1, 3","38 230, 20 180, 31 989, 35 258, 24 487, 28 300, 34 548, 24 557, 37 836, 31 340, 21 874, 40 405, 38 076, 34 265, 30 936, 24 665, 39 007, 24 578, 37 267, 37 878, 20 220, 28 400, 23 882, 32 427, 31 699, 29 670, 32 789, 39 792, 30 935, 31 701"],"handActionClassifierAugmentations":[],"suggestedColumnTypes":["Int","Double","Int","Int"],"styleTransferAlgorithmType":"image","generalRegressorType":{"auto":{}}},"state":"trained","trainingEntity":{"finishTime":"2023-04-18T08:04:49Z","validationResults":{"generalRegressor":{"maximumError":676.63649941958283,"rootMeanSquaredError":174.21773878028176}},"dataURL":"file:\/\/\/Users\/alekseynovikov\/Downloads\/HackingWithSwift-main\/SwiftUI\/project4-files\/BetterRest.csv","dataResult":{"itemsCount":10000,"createdDate":"2023-04-18T08:01:46Z","dataURL":"file:\/\/\/Users\/alekseynovikov\/Downloads\/HackingWithSwift-main\/SwiftUI\/project4-files\/BetterRest.csv","columnTypes":["Int","Double","Int","Int"],"columns":["wake","estimatedSleep","coffee","actualSleep"],"dataSourceID":"FAE8BCD7-345C-4C94-A638-900D5A04FEC2","columnValues":["31 500, 32 400, 26 100, 40 500, 19 800, 27 000, 20 700, 21 600, 41 400, 34 200, 21 600, 78 300, 32 400, 28 800, 18 900, 18 000, 28 800, 18 000, 7 200, 35 100, 24 300, 35 100, 34 200, 27 900, 30 600, 69 300, 35 100, 34 200, 34 200, 23 400","9,00, 5,00, 6,50, 8,75, 6,00, 7,50, 9,25, 6,00, 9,25, 6,75, 5,25, 9,25, 10,00, 8,75, 8,25, 6,25, 10,00, 6,25, 10,00, 9,50, 5,00, 7,50, 6,25, 8,00, 8,00, 6,50, 8,00, 10,00, 8,25, 8,00","6, 2, 10, 4, 3, 1, 1, 3, 5, 8, 3, 8, 2, 3, 1, 2, 3, 2, 1, 4, 2, 1, 1, 4, 3, 7, 4, 4, 1, 3","38 230, 20 180, 31 989, 35 258, 24 487, 28 300, 34 548, 24 557, 37 836, 31 340, 21 874, 40 405, 38 076, 34 265, 30 936, 24 665, 39 007, 24 578, 37 267, 37 878, 20 220, 28 400, 23 882, 32 427, 31 699, 29 670, 32 789, 39 792, 30 935, 31 701"],"targetRange":[19216,45224],"dataAnalysis":{"issues":[{"description":"Data has 10000 rows","severity":"info"}],"regressorAnalysis":{"targetRange":[19216,45224]},"classifierAnalysis":{},"summary":{"canUseValidation":1,"sampleCount":10000}}},"trainingResults":{"generalRegressor":{"maximumError":701.55400784168887,"rootMeanSquaredError":177.18892385784559}},"progress":[],"trainingAccuracy":177.18892385784559,"checkpointMetrics":{},"analysedDataType":"datasource","dataSourceID":"FAE8BCD7-345C-4C94-A638-900D5A04FEC2","snapshottableCheckpoints":{},"featureExtractionCheckpointMayBeAvailable":false,"validationAccuracy":174.21773878028176,"startTime":"2023-04-18T08:04:47Z"},"createdDate":"2023-04-18T07:40:11Z","evaluationContainerEntity":{"testingEvaluationEntity":{"id":"ae535cc2-2976-46f2-96e1-1d4f5a74d255","createdDate":"2023-04-18T07:40:11Z","dataResult":{"createdDate":"2023-04-18T08:01:46Z"},"analysedDataType":"none"},"createdDate":"2023-04-18T10:02:49Z","id":"935ce5dd-e88a-4838-9a18-f2a771caea32","trainingEvaluationEntity":{"evaluationResult":{"generalRegressor":{"maximumError":701.55400784168887,"rootMeanSquaredError":177.18892385784559}},"createdDate":"2023-04-18T07:40:11Z","id":"89e6b028-a0fd-424c-aeb8-a26d5e5556d2","dataURL":"file:\/\/\/Users\/alekseynovikov\/Downloads\/HackingWithSwift-main\/SwiftUI\/project4-files\/BetterRest.csv","dataSourceID":"FAE8BCD7-345C-4C94-A638-900D5A04FEC2","dataResult":{"itemsCount":10000,"createdDate":"2023-04-18T08:01:46Z","targetRange":[19216,45224],"dataURL":"file:\/\/\/Users\/alekseynovikov\/Downloads\/HackingWithSwift-main\/SwiftUI\/project4-files\/BetterRest.csv","dataSourceID":"FAE8BCD7-345C-4C94-A638-900D5A04FEC2","dataAnalysis":{"issues":[{"description":"Data has 10000 rows","severity":"info"}],"regressorAnalysis":{"targetRange":[19216,45224]},"classifierAnalysis":{},"summary":{"canUseValidation":1,"sampleCount":10000}}},"analysedDataType":"none"},"previewType":"tabularRegressor","modifiedDate":"2023-04-18T10:02:49Z","validationEvaluationEntity":{"id":"09a995b5-0a1e-4878-8039-0ca8dbf98419","createdDate":"2023-04-18T07:40:11Z","dataResult":{"createdDate":"2023-04-18T08:01:46Z"},"analysedDataType":"auto","evaluationResult":{"generalRegressor":{"maximumError":676.63649941958283,"rootMeanSquaredError":174.21773878028176}}},"evaluationEntities":[{"id":"14bdefbf-621d-4e1b-97f0-683b4352679a","createdDate":"2023-04-18T10:02:49Z","dataResult":{},"analysedDataType":"none"}]},"activityEntities":["experimentCreated",[{"id":"B2DB4BCD-B164-4CD7-802C-E697AE1B5E87","title":"Model Source Created","createdDate":"2023-04-18T07:40:11Z","event":"experimentCreated","subtitle":"BetterRest 1"}],"trainingDataAdded",[{"id":"9CB02378-10B3-42C1-AD13-EEA3BE98E445","title":"Training Data Added","createdDate":"2023-04-18T08:01:46Z","event":"trainingDataAdded","subtitle":"BetterRest.csv"}],"trainingStarted",[{"id":"7DBC4258-8573-4B4E-9938-C37F4A415676","title":"Training Started","createdDate":"2023-04-18T08:04:47Z","event":"trainingStarted","subtitle":"BetterRest 1"}],"trainingFinished",[{"id":"72C19A2A-4005-4E63-A565-D83FA07D1E42","title":"Training Completed","createdDate":"2023-04-18T08:04:49Z","event":"trainingFinished","subtitle":"BetterRest 1"}]],"evaluationState":"uninitialized","title":"BetterRest 1","evaluationEntity":{"id":"e2c8d90c-31df-4741-8de4-e3af696b9f17","analysedDataType":"none","dataResult":{}},"snapshotRole":{"withoutSnapshots":0},"contentDataResult":{"createdDate":"2023-04-18T08:01:46Z"},"modifiedDate":"2023-04-18T10:02:49Z","preferredFilename":"BetterRest 1"}